zope.app.error-4.1.0-py3.7-nspkg.pth
zope/app/error/README.rst
zope/app/error/__init__.py
zope/app/error/configure.zcml
zope/app/error/error.py
zope/app/error/interfaces.py
zope/app/error/tests.py
zope/app/error/browser/__init__.py
zope/app/error/browser/configure.zcml
zope/app/error/browser/error.gif
zope/app/error/browser/error.pt
zope/app/error/browser/error_config.pt
zope/app/error/browser/error_service.gif
zope/app/error/browser/errorentry.pt
zope/app/error/browser/ftesting.zcml
zope/app/error/browser/tests.py
zope/app/error/browser/texttbentry.pt
zope.app.error-4.1.0.dist-info/LICENSE.txt
zope.app.error-4.1.0.dist-info/METADATA
zope.app.error-4.1.0.dist-info/WHEEL
zope.app.error-4.1.0.dist-info/namespace_packages.txt
zope.app.error-4.1.0.dist-info/top_level.txt
zope.app.error-4.1.0.dist-info/RECORD
