Metadata-Version: 2.1
Name: zope.app.error
Version: 4.1.0
Summary: Error reporting utility management UI for Zope3
Home-page: http://github.com/zopefoundation/zope.app.error
Author: Zope Corporation and Contributors
Author-email: zope-dev@zope.org
License: ZPL 2.1
Keywords: zope3 error reporting utility views UI
Platform: UNKNOWN
Classifier: Development Status :: 5 - Production/Stable
Classifier: Environment :: Web Environment
Classifier: Intended Audience :: Developers
Classifier: License :: OSI Approved :: Zope Public License
Classifier: Programming Language :: Python
Classifier: Programming Language :: Python :: 2
Classifier: Programming Language :: Python :: 2.7
Classifier: Programming Language :: Python :: 3
Classifier: Programming Language :: Python :: 3.5
Classifier: Programming Language :: Python :: 3.6
Classifier: Programming Language :: Python :: 3.7
Classifier: Programming Language :: Python :: 3.8
Classifier: Programming Language :: Python :: 3.9
Classifier: Programming Language :: Python :: 3.10
Classifier: Programming Language :: Python :: Implementation :: CPython
Classifier: Programming Language :: Python :: Implementation :: PyPy
Classifier: Natural Language :: English
Classifier: Operating System :: OS Independent
Classifier: Topic :: Internet :: WWW/HTTP
Classifier: Framework :: Zope :: 3
Requires-Dist: setuptools
Requires-Dist: zope.annotation
Requires-Dist: zope.component
Requires-Dist: zope.error
Requires-Dist: zope.publisher
Requires-Dist: zope.security
Requires-Dist: zope.traversing
Provides-Extra: browser
Requires-Dist: zope.browsermenu ; extra == 'browser'
Requires-Dist: zope.browserpage ; extra == 'browser'
Requires-Dist: zope.browserresource ; extra == 'browser'
Provides-Extra: test
Requires-Dist: zope.testing ; extra == 'test'
Requires-Dist: zope.testrunner ; extra == 'test'
Requires-Dist: zope.browserpage ; extra == 'test'
Requires-Dist: zope.browsermenu ; extra == 'test'
Requires-Dist: zope.browserresource ; extra == 'test'
